<FileConfig ProductName="6TA-E" PackageHead="6A-ELatheCE7_ARM"><Files><File Category="Software" Usage="Test" Hardware="Common"><Version>10.116.54R</Version><Name>package_7a248a2c.zip</Name><Hash>7fef3ba6bab94d9944e833b36fc7b6bf</Hash><URL>http://www.syntecclub.com.tw/cncrel/QCREL/OQCDB/6TA_E/Software/Test/Common/package_7a248a2c.zip</URL></File><File Category="Packing" Usage="Test" Hardware="Common"><Version>10.116.54R</Version><Name>Test.zip</Name><Hash>4b32b971afd5499eb0f1431053957a7e</Hash></File><File Category="Software" Usage="Delivery" Hardware="Common"><Version>10.116.54R</Version><Name>package_6fe8f024.zip</Name><Hash>4f7c4c288426b91679e486460d8463dd</Hash><URL>http://www.syntecclub.com.tw/cncrel/QCREL/OQCDB/6TA_E/Software/Delivery/Common/package_6fe8f024.zip</URL></File><File Category="Packing" Usage="Delivery" Hardware="Common"><Version>10.116.54R</Version><Name>Delivery.zip</Name><Hash>3b1c3b44797fc84c850001cf0d03d134</Hash></File><File Category="Image" Usage="Common" Hardware="AM335x"><Version>7.55.0</Version><Name>WCE7_AM335x_7.55.0.bin</Name><Hash>32cea1effb04f7cdb7d49c6064d70eae</Hash><URL>http://www.syntecclub.com.tw/cncrel/7.55.0/ARMCE7_Image/WCE7_AM335x_7.55.0.bin</URL></File></Files></FileConfig>
