<FileConfig ProductName="F01-6B-4012-T2" PackageHead="6BLatheCE7_ARM"><Files><File Category="Image" Usage="Common" Hardware="AM335x"><Version>7.60.0</Version><Name>WCE7_AM335x_7.60.0.bin</Name><Hash>2ae106883481d82bb36c995de954960a</Hash><URL>http://www.syntecclub.com.tw/cncrel/7.60.0/ARMCE7_Image/WCE7_AM335x_7.60.0.bin</URL></File><File Category="Packing" Usage="Common" Hardware="Common"><Version>10.116.26K</Version></File><File Category="Software" Usage="Test" Hardware="Common"><Version>10.116.26K</Version><Name>package_8d04bf18.zip</Name><Hash>0f2d00d13a8772bc5ecf9e5d4f497de0</Hash><URL>http://www.syntecclub.com.tw/cncrel/QCREL/OQCDB/F01_6B_4012_T2/Software/Test/Common/package_8d04bf18.zip</URL></File><File Category="Software" Usage="Delivery" Hardware="Common"><Version>10.116.26K</Version><Name>package_CBD96021.zip</Name><Hash>3be0fba3bad99ab534edd98e8941c89a</Hash><URL>http://www.syntecclub.com.tw/cncrel/QCREL/OQCDB/F01_6B_4012_T2/Software/Delivery/Common/package_CBD96021.zip</URL></File></Files></FileConfig>
